{
  "date": "2025-04-19T00:00:00",
  "formatted_date": "19/04/2025",
  "day_of_week": "Saturday",
  "readings": [
    {
      "type": "primeira_leitura",
      "title": "Leitura do Dia",
      "content": "Da Carta aos Hebreus\n(4, 1-16)\nPortanto, enquanto ainda está em pé a promessa de entrar no repouso de Deus, devemos cuidar para que ninguém de vós falte ao apelo. Pois a nós foi anunciada a boa nova exatamente como àqueles. Mas a eles de nada adiantou a palavra do anúncio: não se uniram, pela fé, aos que a ouviram. Nós, porém, que acreditamos, podemos entrar no repouso, do qual ele falou:\nâPor isso jurei na minha ira:\njamais entrarão no meu repousoâ,\numa vez que as obras estão terminadas desde a criação do mundo. De fato, numa passagem da Escritura a respeito do sétimo dia, ele disse: âE Deus repousou no sétimo dia de todas as suas obrasâ. Também diz, no texto aqui referido: âJamais entrarão no meu repousoâ. Daí se confirma que alguns entram nesse repouso, enquanto os primeiros a receberem a boa-nova não entraram, por causa da desobediência.. Por isso, Deus marca de novo um dia, um âhojeâ, quando fala por meio de Davi, muito tempo depois, no texto que já citamos:\nâHoje, se ouvirdes a sua voz,\nnão endureçais os vossos c"
    }
  ],
  "title": "Palavra do dia",
  "source_url": "https://www.vaticannews.va/pt/palavra-do-dia/2025/04/19.html"
}