{
  "date": "2025-06-17T00:00:00",
  "formatted_date": "17/06/2025",
  "day_of_week": "Tuesday",
  "title": "São Rainério",
  "content": "Nasceu em Pisa, Itália, no ano de 1118. O santo de hoje teve a graça de nascer em um lar cristão, porém, optou por uma vida no pecado e a consequência foi o vazio existencial. Providencialmente encontrou com Alberto de Córsega, uma grande testemunha em seu tempo, que deixara tudo por causa de Jesus.\n\nRainério se retirou por um tempo em penitência e nesse momento acontece seu chamado para deixar todos os seus bens. E ele o fez: foi para a Terra Santa, onde ficou muitos anos, visitando os lugares santos e sendo instrumento de conversão para muitos.\n\nSão Rainério, obediente a Deus, voltou para Pisa. Tornou-se monge e depois formador dos monges. Foi um apóstolo para o povo, consumindo-se pelo Evangelho, vindo a falecer em 1160.\n\nSão Rainério, rogai por nós!",
  "date_in_content": "17 de junho",
  "image": {
    "original_url": "https://assets.ofertorio.com/api/saints/306.jpg",
    "local_path": "../santos/imagens/2025-06-17-santo.webp",
    "filename": "2025-06-17-santo.webp",
    "width": 300,
    "height": 299,
    "format": "WebP"
  }
}