{
  "date": "2025-05-18T00:00:00",
  "formatted_date": "18/05/2025",
  "day_of_week": "Sunday",
  "title": "Santo do Dia",
  "content": "O santo de hoje governou a Igreja por apenas dois anos e meio. Foi eleito Papa em 523. Nasceu na Toscana, Florência, no século V. De Florência foi para Roma e tornou-se um sacerdote, um presbítero cardeal. Com a morte do Papa, ele foi eleito o sucessor de Pedro.\n\nMarcou a Igreja com muitos trabalhos pastorais, foi o precursor do canto gregoriano e da restauração de muitas igrejas, mas o objetivo dele como Papa, foi de confirmar a fé dos irmãos; sem dúvida nenhuma, era o serviço da salvação das almas.\n\nPapa João I viveu num tempo e contexto político-religioso complexo. Quem reinava na Itália era Teodorico, um cristão ariano, ou seja, não era fiel à doutrina católica, mas se dizia cristão. Por outro lado, existia um conflito entre Teodorico e Justino; e os dois imperadores se chocavam. No meio deste contexto complexo, a vítima foi o Papa João I, que foi forçado por Teodorico a uma missão. Nunca um Papa tinha saído da Itália; ele foi o primeiro.\n\nA missão não agradou, porque Teodorico queria que o Papa fosse o porta-voz de uma mensagem ariana, por interesses econômicos e políticos. Mas o que podemos perceber é que este homem santo, autoridade máxima da Igreja de Cristo, não perdeu sua paz, não perdeu sua obediência a Deus. Tornou-se santo em meio aos conflitos.\n\nEle viveu uma vida de oração, uma vida penitencial, oferecendo e sempre buscando ser dócil à vontade de Deus. Papa João I, por causa do ódio de Teodorico, foi aprisionado para morrer de fome e de sede. Foi mártir.\n\nHoje, podemos recordar este Pastor da Igreja como o pastor que, a exemplo de Cristo, deu a vida pelo rebanho.\n\nSão João I, rogai por nós!",
  "date_in_content": "18 de maio",
  "image": {
    "original_url": "https://assets.ofertorio.com/24/0d78a157e24b9290b920e3d2c7dd5595.png",
    "local_path": "C:\\Users\\edima\\OneDrive\\Documentos\\Projetos\\cursor-ai\\church-scraper-v1\\output\\santos\\imagens\\2025-05-18-e98ee7fd.webp",
    "width": 400,
    "height": 156,
    "format": "WebP",
    "size_reduction": "Optimized for web"
  }
}